pyalienvaultcli/__init__.py
pyalienvaultcli/pyalienvaultcli.py
pyalienvaultcli/requirements.txt
pyalienvaultcli-1.3.dist-info/METADATA
pyalienvaultcli-1.3.dist-info/WHEEL
pyalienvaultcli-1.3.dist-info/entry_points.txt
pyalienvaultcli-1.3.dist-info/top_level.txt
pyalienvaultcli-1.3.dist-info/RECORD
