Metadata-Version: 2.4
Name: pyalienvaultcli
Version: 1.3
Summary: A simple Python script to interact with Alienvault OTX APIs from CLI.
Author-email: tdebize@mail.com
License-Expression: LGPL-3.0-or-later
Project-URL: Homepage, https://github.com/maaaaz/pyalienvaultcli
Keywords: alienvault,otx,cli,malware,phishing,threat,open,threat,exchange,ioc,api
Classifier: Topic :: Security
Classifier: Programming Language :: Python :: 3
Requires-Python: >=3
Requires-Dist: OTXv2
Requires-Dist: validators
